torchsphharm/__init__.py
torchsphharm/main.py
torchsphharm/py.typed
torchsphharm-0.0.1.dist-info/LICENSE
torchsphharm-0.0.1.dist-info/METADATA
torchsphharm-0.0.1.dist-info/WHEEL
torchsphharm-0.0.1.dist-info/RECORD
